{
  "tool": "derive_streamwise_momentum_budget.py",
  "generated_at": "2026-07-04T10:21:47-05:00",
  "method": "bulk streamwise momentum budget from section-mean p_rgh/rho/u; friction driver = d(p_rgh)/ds + gh*d(rho)/ds (- inertia); gh = g.x = -9.81*y (g verified in constant/g). Isothermal legs reduce to legacy d(p_rgh)/ds friction (consistency check).",
  "cases": [
    {
      "source_id": "viscosity_screening_salt_test_1_jin_coarse_mesh",
      "section_json": "work_products/2026-07-04_salt1_friction/section_mean_pressure_viscosity_screening_salt_test_1_jin_coarse_mesh.json",
      "legs": [
        {
          "span": "lower_leg",
          "n_stations_used": 3,
          "d_h_m": 0.02182132919954016,
          "rho_mean_kg_m3": 1968.46462439958,
          "u_bulk_mean_m_s": 0.01167608743116236,
          "bulk_T_K": 433.6873090575161,
          "bulk_T_C": 160.5373090575161,
          "gh_mean_m2_s2": 1.2038125541598454,
          "u_along_tangent_mean_m_s": -0.011660079983941134,
          "flow_orientation_sigma": -1.0,
          "grad_p_rgh_pa_m": 8.519159526451148,
          "grad_rho_kg_m4": 11.844615307696538,
          "grad_u_per_s": -0.0003029269458663447,
          "buoyancy_source_grad_pa_m": 14.258696606598972,
          "inertial_grad_pa_m": -0.006962462339415425,
          "friction_grad_raw_pa_m": 8.519159526451148,
          "friction_grad_corrected_pa_m": 22.777856133050122,
          "friction_grad_corrected_noinertia_pa_m": 22.770893670710706,
          "f_raw_buoyancy_embedded": 1.3854334098396668,
          "f_corrected": 3.70426246782526,
          "f_corrected_noinertia": 3.70313019322589,
          "Re": 44.625505712186474,
          "f_lam_64_re": 1.4341574168989792,
          "f_corrected_over_flam": 2.5828841549589705,
          "buoyancy_fraction_of_raw_grad": 1.6737210475196678,
          "source_id": "viscosity_screening_salt_test_1_jin_coarse_mesh"
        },
        {
          "span": "right_leg",
          "n_stations_used": 3,
          "d_h_m": 0.02181495869709446,
          "rho_mean_kg_m3": 1974.6639636805558,
          "u_bulk_mean_m_s": 0.011112150280316058,
          "bulk_T_K": 425.4182157122104,
          "bulk_T_C": 152.2682157122104,
          "gh_mean_m2_s2": -2.2497484190935495,
          "u_along_tangent_mean_m_s": -0.011112149499429397,
          "flow_orientation_sigma": -1.0,
          "grad_p_rgh_pa_m": 8.809918462883333,
          "grad_rho_kg_m4": -2.4165130672214534,
          "grad_u_per_s": -0.0007001309090515677,
          "buoyancy_source_grad_pa_m": 5.4365464527003695,
          "inertial_grad_pa_m": -0.015362806408536163,
          "friction_grad_raw_pa_m": 8.809918462883333,
          "friction_grad_corrected_pa_m": 14.246464915583703,
          "friction_grad_corrected_noinertia_pa_m": 14.231102109175167,
          "f_raw_buoyancy_embedded": 1.5764015990865907,
          "f_corrected": 2.549189322111728,
          "f_corrected_noinertia": 2.5464403803716986,
          "Re": 37.52802901278211,
          "f_lam_64_re": 1.7053919878979384,
          "f_corrected_over_flam": 1.4947820443638016,
          "buoyancy_fraction_of_raw_grad": 0.6170938443533656,
          "source_id": "viscosity_screening_salt_test_1_jin_coarse_mesh"
        },
        {
          "span": "left_lower_leg",
          "n_stations_used": 3,
          "d_h_m": 0.021814958682552486,
          "rho_mean_kg_m3": 1969.1667328472224,
          "u_bulk_mean_m_s": 0.011803330409284633,
          "bulk_T_K": 432.75078985297785,
          "bulk_T_C": 159.60078985297787,
          "gh_mean_m2_s2": -1.678359927379258,
          "u_along_tangent_mean_m_s": 0.011803303169438754,
          "flow_orientation_sigma": 1.0,
          "grad_p_rgh_pa_m": -15.01050603395797,
          "grad_rho_kg_m4": -2.4242218543130765,
          "grad_u_per_s": -0.0017698005269053592,
          "buoyancy_source_grad_pa_m": 4.0687168153561055,
          "inertial_grad_pa_m": -0.04113498797601901,
          "friction_grad_raw_pa_m": 15.01050603395797,
          "friction_grad_corrected_pa_m": 10.941789218601865,
          "friction_grad_corrected_noinertia_pa_m": 10.982924206577884,
          "f_raw_buoyancy_embedded": 2.3871961466891776,
          "f_corrected": 1.740127681334684,
          "f_corrected_noinertia": 1.7466695850232274,
          "Re": 44.49036870791845,
          "f_lam_64_re": 1.4385135897650856,
          "f_corrected_over_flam": 1.2096706584599268,
          "buoyancy_fraction_of_raw_grad": 0.27105793809692547,
          "source_id": "viscosity_screening_salt_test_1_jin_coarse_mesh"
        },
        {
          "span": "test_section_span",
          "n_stations_used": 3,
          "d_h_m": 0.02069210493406325,
          "rho_mean_kg_m3": 1968.2766298913045,
          "u_bulk_mean_m_s": 0.012387111289694948,
          "bulk_T_K": 433.93806870574275,
          "bulk_T_C": 160.78806870574277,
          "gh_mean_m2_s2": -4.406060947404615,
          "u_along_tangent_mean_m_s": -0.012387057647478184,
          "flow_orientation_sigma": -1.0,
          "grad_p_rgh_pa_m": 7.03230075330785,
          "grad_rho_kg_m4": -2.442246578296464,
          "grad_u_per_s": -0.00027760152738646066,
          "buoyancy_source_grad_pa_m": 10.760687272564597,
          "inertial_grad_pa_m": -0.006768275477360276,
          "friction_grad_raw_pa_m": 7.03230075330785,
          "friction_grad_corrected_pa_m": 17.792988025872447,
          "friction_grad_corrected_noinertia_pa_m": 17.786219750395087,
          "f_raw_buoyancy_embedded": 0.9636201859977802,
          "f_corrected": 2.4381327011479854,
          "f_corrected_noinertia": 2.4372052597453537,
          "Re": 45.05584492616276,
          "f_lam_64_re": 1.420459434394867,
          "f_corrected_over_flam": 1.7164395139426558,
          "buoyancy_fraction_of_raw_grad": 1.5301801856956971,
          "source_id": "viscosity_screening_salt_test_1_jin_coarse_mesh"
        },
        {
          "span": "left_upper_leg",
          "n_stations_used": 3,
          "d_h_m": 0.021814958682552486,
          "rho_mean_kg_m3": 1969.031351736111,
          "u_bulk_mean_m_s": 0.011411855181248124,
          "bulk_T_K": 432.9313702332785,
          "bulk_T_C": 159.78137023327855,
          "gh_mean_m2_s2": -7.385096057753868,
          "u_along_tangent_mean_m_s": 0.011411807558279382,
          "flow_orientation_sigma": 1.0,
          "grad_p_rgh_pa_m": -18.28166454933965,
          "grad_rho_kg_m4": -1.2498688335004768,
          "grad_u_per_s": -0.0009616069428675825,
          "buoyancy_source_grad_pa_m": 9.230401394993798,
          "inertial_grad_pa_m": -0.021607597097350942,
          "friction_grad_raw_pa_m": 18.28166454933965,
          "friction_grad_corrected_pa_m": 9.05126315434585,
          "friction_grad_corrected_noinertia_pa_m": 9.072870751443201,
          "f_raw_buoyancy_embedded": 3.110534277550592,
          "f_corrected": 1.5400273985303172,
          "f_corrected_noinertia": 1.5437038236854457,
          "Re": 43.12789119109775,
          "f_lam_64_re": 1.4839584833030408,
          "f_corrected_over_flam": 1.037783344923826,
          "buoyancy_fraction_of_raw_grad": 0.5048993963368182,
          "source_id": "viscosity_screening_salt_test_1_jin_coarse_mesh"
        },
        {
          "span": "upper_leg",
          "n_stations_used": 3,
          "d_h_m": 0.021821740388825197,
          "rho_mean_kg_m3": 1972.1628515990496,
          "u_bulk_mean_m_s": 0.011489016376130897,
          "bulk_T_K": 428.75436628111277,
          "bulk_T_C": 155.6043662811128,
          "gh_mean_m2_s2": -8.110934500772084,
          "u_along_tangent_mean_m_s": 0.011478285488272857,
          "flow_orientation_sigma": 1.0,
          "grad_p_rgh_pa_m": 103.0364462247684,
          "grad_rho_kg_m4": 15.181503591881036,
          "grad_u_per_s": 0.0010973611740290163,
          "buoyancy_source_grad_pa_m": -123.1361812569832,
          "inertial_grad_pa_m": 0.024864241351830036,
          "friction_grad_raw_pa_m": -103.0364462247684,
          "friction_grad_corrected_pa_m": 20.09973503221481,
          "friction_grad_corrected_noinertia_pa_m": 20.07487079086298,
          "f_raw_buoyancy_embedded": -17.274352624254693,
          "f_corrected": 3.369777620660017,
          "f_corrected_noinertia": 3.3656090600333326,
          "Re": 40.83391440840246,
          "f_lam_64_re": 1.5673246351035752,
          "f_corrected_over_flam": 2.1500189208965814,
          "buoyancy_fraction_of_raw_grad": 1.1950740322348494,
          "source_id": "viscosity_screening_salt_test_1_jin_coarse_mesh"
        }
      ]
    }
  ]
}
