{
  "candidate_freeze": false,
  "candidate_id": "PASSIVE-H2-CAND001",
  "coefficient_admission": false,
  "decision": "passive_h2_one_train_repair_preflight_pass_dry_no_execution_no_release",
  "dry_preflight_gate_pass_rows": 6,
  "dry_preflight_gate_total_rows": 6,
  "exactly_one_candidate_named": true,
  "exactly_one_train_case_declared": true,
  "final_score_claim": false,
  "fitting_or_model_selection": false,
  "fluid_or_external_edit": false,
  "generated_at_utc": "2026-07-22T17:05:32+00:00",
  "native_output_mutation": false,
  "numeric_q_loss_release": false,
  "passive_operator_family_rows": 5,
  "q_loss_operator_admissible_rows": 5,
  "qwall_release": false,
  "registry_or_admission_mutation": false,
  "repair_run": false,
  "runtime_leakage_relaxation": false,
  "runtime_setup_input_allowed_rows": 5,
  "scenario_id": "salt_2__V00__nominal",
  "scheduler_action": false,
  "setup_uq_baseline_roots_accepted": 3,
  "setup_uq_variant_roots_accepted": 33,
  "solver_or_sampler_launch": false,
  "source_backed_operator_rows": 5,
  "source_property_release": false,
  "task_id": "TODO-THERMAL-PASSIVE-H2-ONE-TRAIN-REPAIR-PREFLIGHT-2026-07-22",
  "thesis_current_or_latex_edit": false,
  "train_case_id": "salt_2",
  "train_case_name": "Salt 2",
  "validation_holdout_external_scoring": false
}
