{
  "blocker_register_change": false,
  "clipped_k_rows": 0,
  "component_k_admitted_rows": 0,
  "date": "2026-07-21",
  "external_test_rows_consumed": 0,
  "f6_fit_rows": 0,
  "fitting_or_model_selection": false,
  "fluid_or_external_edit": false,
  "generated_index_refresh": false,
  "hidden_global_multiplier_rows": 0,
  "holdout_rows_consumed": 0,
  "native_output_mutation": false,
  "registry_or_admission_mutation": false,
  "row_count": 3,
  "s11_s15_s6_trigger": false,
  "salt2_frozen_K_eff_recirc": "-7.56139965813",
  "salt2_frozen_all_case_max_abs_error_pa": "0.47046606946166093438399",
  "salt2_frozen_transfer_max_abs_error_pa": "0.47046606946166093438399",
  "salt2_residual_pa": "-1.25366731683",
  "salt3_residual_pa": "-1.84957005859",
  "salt4_residual_pa": "-1.67833900273",
  "scheduler_action": false,
  "status": "complete",
  "task": "TODO-TWO-TAP-SECTION-EFFECTIVE-HYBRID-PRESSURE-SCORECARD-2026-07-21",
  "thesis_current_file_edit": false,
  "three_level_rows": 9,
  "validation_rows_consumed": 0
}
