{
  "date": "2026-07-17",
  "external_fluid_edit": false,
  "generated_index_refresh_note": "Skipped because active board rows own generated docs index files.",
  "generated_index_refreshed": false,
  "native_solver_outputs_mutated": false,
  "outputs": [
    "README.md",
    "runtime_thermal_input_audit.csv",
    "segment_thermal_model_scorecard.csv",
    "source_manifest.csv",
    "source_sink_ownership_contract.csv",
    "summary.json",
    "thermal_evidence_rollup.csv",
    "thermal_model_slot_admission.csv"
  ],
  "package": "work_products/2026-07/2026-07-17/2026-07-17_predict_segment_thermal_models",
  "registry_mutated": false,
  "scheduler_action": false,
  "summary": {
    "admitted_setup_model_rows": 2,
    "all_sources_present": true,
    "date": "2026-07-17",
    "diagnostic_source_sink_rows": 52,
    "evidence_rollup_rows": 7,
    "external_fluid_edit": false,
    "generated_index_refreshed": false,
    "native_solver_outputs_mutated": false,
    "registry_mutated": false,
    "residual_internal_nu_fit_admitted_rows": 0,
    "runtime_audit_pass_rows": 5,
    "runtime_audit_rows": 5,
    "scheduler_action": false,
    "scoreable_predictive_thermal_rows": 2,
    "segment_rows": 7,
    "task": "TODO-PREDICT-SEGMENT-THERMAL-MODELS",
    "thermal_slot_rows": 23,
    "train_validation_holdout_improvement_status": "not_run_in_this_scorecard"
  },
  "task": "TODO-PREDICT-SEGMENT-THERMAL-MODELS"
}
